remote_gym/__init__.py
remote_gym/remote_environment.py
remote_gym/remote_environment_management.py
remote_gym/repo_manager.py
remote_gym-0.7.1.dist-info/LICENSE
remote_gym-0.7.1.dist-info/METADATA
remote_gym-0.7.1.dist-info/WHEEL
remote_gym-0.7.1.dist-info/RECORD
