Metadata-Version: 2.1
Name: remote-gym
Version: 0.7.1
Summary: This is a module to run Gym environments remotely, to enable splitting environment hosting and agent training into separate processes (or even separate machines).
Home-page: https://github.com/alexander-zap/remote-gym
License: MIT
Keywords: reinforcement learning,rl,imitation learning,gym,gymnasium,dm_env
Author: Alexander Zap
Requires-Python: >=3.8,<3.12
Classifier: Development Status :: 5 - Production/Stable
Classifier: Intended Audience :: Developers
Classifier: License :: OSI Approved :: MIT License
Classifier: Operating System :: OS Independent
Classifier: Programming Language :: Python
Classifier: Programming Language :: Python :: 3
Classifier: Programming Language :: Python :: 3.8
Classifier: Programming Language :: Python :: 3.9
Classifier: Programming Language :: Python :: 3.10
Classifier: Programming Language :: Python :: 3.11
Classifier: Topic :: Software Development :: Libraries :: Python Modules
Requires-Dist: dm-env-rpc (>=1.1.6,<2.0.0)
Requires-Dist: fasteners (>=0.19,<0.20)
Requires-Dist: gitpython (>=3.1.43,<4.0.0)
Requires-Dist: gym (>=0.26.2,<0.27.0)
Requires-Dist: gymnasium (>=0.29.0,<0.30.0)
Requires-Dist: opencv-python (>=4.9.0.80,<5.0.0.0)
Requires-Dist: protobuf (>=3.20,<5)
Requires-Dist: psutil (>=6.0.0,<7.0.0)
Requires-Dist: setuptools (>=68.0,<69.0)
